<?xml version="1.0" encoding="UTF-8"?>
<site>
   <description name="The Onotoa Update Site" url="file:/home/mai00ckx/projects/onotoa-update-site">
      This is the onotoa update site used to update the onotoa plugins in the Onotoa application or in any other eclipse instance.
   </description>
   <feature url="features/de.topicmapslab.aranuka.majortom_feature_1.1.2.jar" id="de.topicmapslab.aranuka.majortom_feature" version="1.1.2">
      <category name="onotoa"/>
   </feature>
   <feature url="features/de.topicmapslab.onotoa.aranuka.codegen_feature_1.0.0.qualifier.jar" id="de.topicmapslab.onotoa.aranuka.codegen_feature" version="1.0.0.qualifier">
      <category name="onotoa"/>
   </feature>
   <feature url="features/de.topicmapslab.tmcledit.application_feature_1.2.0.qualifier.jar" id="de.topicmapslab.tmcledit.application_feature" version="1.2.0.qualifier">
      <category name="onotoa"/>
   </feature>
   <feature url="features/de.topicmapslab.tmcledit.core_feature_1.2.0.qualifier.jar" id="de.topicmapslab.tmcledit.core_feature" version="1.2.0.qualifier">
      <category name="onotoa"/>
   </feature>
   <feature url="features/de.topicmapslab.tmcledit.doc_feature_1.2.0.qualifier.jar" id="de.topicmapslab.tmcledit.doc_feature" version="1.2.0.qualifier">
      <category name="onotoa"/>
   </feature>
   <feature url="features/de.topicmapslab.tmcledit.export_feature_1.2.0.qualifier.jar" id="de.topicmapslab.tmcledit.export_feature" version="1.2.0.qualifier">
      <category name="onotoa"/>
   </feature>
   <feature url="features/de.topicmapslab.tmcledit.import_feature_1.2.0.qualifier.jar" id="de.topicmapslab.tmcledit.import_feature" version="1.2.0.qualifier">
      <category name="onotoa"/>
   </feature>
   <category-def name="onotoa" label="Onotoa"/>
</site>
